README.rst
etherws.py
setup.py
etherws.egg-info/PKG-INFO
etherws.egg-info/SOURCES.txt
etherws.egg-info/dependency_links.txt
etherws.egg-info/entry_points.txt
etherws.egg-info/requires.txt
etherws.egg-info/top_level.txt