Metadata-Version: 1.1
Name: etherws
Version: 1.1
Summary: Ethernet over WebSocket
Home-page: UNKNOWN
Author: Atzm WATANABE
Author-email: atzm@atzm.org
License: BSD-2
Keywords: http,websocket,ethernet,network
Platform: Linux
Classifier: Development Status :: 3 - Alpha
Classifier: License :: OSI Approved :: BSD License
Classifier: Operating System :: POSIX :: Linux
Classifier: Programming Language :: Python :: 2.7
Classifier: Topic :: System :: Networking
